yamk/__init__.py
yamk/__main__.py
yamk/__version__.py
yamk/command/__init__.py
yamk/command/make.py
yamk/lib/__init__.py
yamk/lib/functions.py
yamk/lib/parser.py
yamk/lib/types.py
yamk/lib/utils.py
yamk/py.typed
yamk-8.1.2.dist-info/METADATA
yamk-8.1.2.dist-info/WHEEL
yamk-8.1.2.dist-info/entry_points.txt
yamk-8.1.2.dist-info/RECORD
