Metadata-Version: 2.3
Name: yamk
Version: 8.1.2
Summary: Yet another make
Home-page: https://yamk.readthedocs.io/en/stable/
License: BSD-3-Clause
Keywords: build,cli,make
Author: Stephanos Kuma
Author-email: "Stephanos Kuma" <stephanos@kuma.ai>
Requires-Python: >=3.9
Classifier: Development Status :: 5 - Production/Stable
Classifier: Intended Audience :: Developers
Classifier: License :: OSI Approved :: BSD License
Classifier: Operating System :: OS Independent
Classifier: Programming Language :: Python :: 3 :: Only
Classifier: Topic :: Software Development :: Build Tools
Requires-Dist: dj-settings (~=6.0)
Requires-Dist: pyutilkit (~=0.5)
Project-URL: Documentation, https://yamk.readthedocs.io/en/stable/
Project-URL: Repository, https://github.com/spapanik/yamk
